odoo/addons/portal_odoo_debranding/README.rst
odoo/addons/portal_odoo_debranding/__init__.py
odoo/addons/portal_odoo_debranding/__manifest__.py
odoo/addons/portal_odoo_debranding/i18n/it.po
odoo/addons/portal_odoo_debranding/i18n/portal_odoo_debranding.pot
odoo/addons/portal_odoo_debranding/readme/CONTRIBUTORS.rst
odoo/addons/portal_odoo_debranding/readme/DESCRIPTION.rst
odoo/addons/portal_odoo_debranding/static/description/icon.png
odoo/addons/portal_odoo_debranding/static/description/index.html
odoo/addons/portal_odoo_debranding/views/portal_templates.xml
odoo12_addon_portal_odoo_debranding-12.0.1.0.0.99.dev6.dist-info/METADATA
odoo12_addon_portal_odoo_debranding-12.0.1.0.0.99.dev6.dist-info/WHEEL
odoo12_addon_portal_odoo_debranding-12.0.1.0.0.99.dev6.dist-info/top_level.txt
odoo12_addon_portal_odoo_debranding-12.0.1.0.0.99.dev6.dist-info/RECORD
